sfisop/dataspace_sdk/__init__.py
sfisop/dataspace_sdk/client.py
sfisop/dataspace_sdk/config.py
sfisop/dataspace_sdk/main.py
sfisop/dataspace_sdk/sop_datasources.py
sfisop_dataspace_sdk-1.0.1.dist-info/LICENSE
sfisop_dataspace_sdk-1.0.1.dist-info/METADATA
sfisop_dataspace_sdk-1.0.1.dist-info/WHEEL
sfisop_dataspace_sdk-1.0.1.dist-info/RECORD
