Metadata-Version: 2.1
Name: sfisop-dataspace-sdk
Version: 1.0.1
Summary: SDK for the SmartOcean Platform Data Space Service
License: MIT
Author: Smart Ocean Consotrium
Requires-Python: >=3.9,<4.0.0
Classifier: License :: OSI Approved :: MIT License
Classifier: Programming Language :: Python :: 3
Classifier: Programming Language :: Python :: 3.9
Classifier: Programming Language :: Python :: 3.10
Classifier: Programming Language :: Python :: 3.11
Classifier: Programming Language :: Python :: 3.12
Classifier: Programming Language :: Python :: 3.13
Requires-Dist: certifi (==2024.7.4)
Requires-Dist: charset-normalizer (>=3.3.2,<4.0.0)
Requires-Dist: idna (>=3.7,<4.0)
Requires-Dist: python-decouple (>=3.8,<4.0)
Requires-Dist: pyyaml (>=6.0.1,<7.0.0)
Requires-Dist: requests (>=2.32.0,<3.0.0)
Requires-Dist: urllib3 (>=2.2.2,<3.0.0)
